{
  "indexes": [
    {
      "collectionGroup": "sai-wardrobeItems",
      "queryScope": "COLLECTION",
      "fields": [
        { "fieldPath": "userId", "order": "ASCENDING" },
        { "fieldPath": "status", "order": "ASCENDING" },
        { "fieldPath": "createdAt", "order": "DESCENDING" }
      ]
    },
    {
      "collectionGroup": "sai-wardrobeItems",
      "queryScope": "COLLECTION",
      "fields": [
        { "fieldPath": "userId", "order": "ASCENDING" },
        { "fieldPath": "piece_type", "order": "ASCENDING" },
        { "fieldPath": "createdAt", "order": "DESCENDING" }
      ]
    },
    {
      "collectionGroup": "sai-wardrobeItems",
      "queryScope": "COLLECTION",
      "fields": [
        { "fieldPath": "brand_id", "order": "ASCENDING" },
        { "fieldPath": "createdAt", "order": "DESCENDING" }
      ]
    },
    {
      "collectionGroup": "sai-wardrobeItems",
      "queryScope": "COLLECTION",
      "fields": [
        { "fieldPath": "market_id", "order": "ASCENDING" },
        { "fieldPath": "gender", "order": "ASCENDING" },
        { "fieldPath": "createdAt", "order": "DESCENDING" }
      ]
    }
  ],
  "fieldOverrides": []
}
